stooqpy_suli/__init__.py
stooqpy_suli/stooq/__init__.py
stooqpy_suli/stooq/stooq.py
stooqpy_suli-0.0.6.dist-info/LICENSE
stooqpy_suli-0.0.6.dist-info/METADATA
stooqpy_suli-0.0.6.dist-info/WHEEL
stooqpy_suli-0.0.6.dist-info/top_level.txt
stooqpy_suli-0.0.6.dist-info/RECORD
